odoo/addons/contract_payment_mode/README.rst
odoo/addons/contract_payment_mode/__init__.py
odoo/addons/contract_payment_mode/__manifest__.py
odoo/addons/contract_payment_mode/hooks.py
odoo/addons/contract_payment_mode/i18n/ca.po
odoo/addons/contract_payment_mode/i18n/contract_payment_mode.pot
odoo/addons/contract_payment_mode/i18n/de.po
odoo/addons/contract_payment_mode/i18n/el_GR.po
odoo/addons/contract_payment_mode/i18n/es.po
odoo/addons/contract_payment_mode/i18n/es_AR.po
odoo/addons/contract_payment_mode/i18n/es_MX.po
odoo/addons/contract_payment_mode/i18n/fi.po
odoo/addons/contract_payment_mode/i18n/fr.po
odoo/addons/contract_payment_mode/i18n/gl.po
odoo/addons/contract_payment_mode/i18n/hi_IN.po
odoo/addons/contract_payment_mode/i18n/hr.po
odoo/addons/contract_payment_mode/i18n/hr_HR.po
odoo/addons/contract_payment_mode/i18n/hu.po
odoo/addons/contract_payment_mode/i18n/it.po
odoo/addons/contract_payment_mode/i18n/nl.po
odoo/addons/contract_payment_mode/i18n/pt.po
odoo/addons/contract_payment_mode/i18n/pt_BR.po
odoo/addons/contract_payment_mode/i18n/pt_PT.po
odoo/addons/contract_payment_mode/i18n/ro.po
odoo/addons/contract_payment_mode/i18n/ru.po
odoo/addons/contract_payment_mode/i18n/sk_SK.po
odoo/addons/contract_payment_mode/i18n/sl.po
odoo/addons/contract_payment_mode/i18n/sv.po
odoo/addons/contract_payment_mode/i18n/tr.po
odoo/addons/contract_payment_mode/i18n/tr_TR.po
odoo/addons/contract_payment_mode/i18n/zh_CN.po
odoo/addons/contract_payment_mode/models/__init__.py
odoo/addons/contract_payment_mode/models/contract.py
odoo/addons/contract_payment_mode/readme/CONFIGURE.md
odoo/addons/contract_payment_mode/readme/CONTRIBUTORS.md
odoo/addons/contract_payment_mode/readme/DESCRIPTION.md
odoo/addons/contract_payment_mode/readme/USAGE.md
odoo/addons/contract_payment_mode/static/description/icon.png
odoo/addons/contract_payment_mode/static/description/index.html
odoo/addons/contract_payment_mode/tests/__init__.py
odoo_addon_contract_payment_mode-18.0.1.0.0.5.dist-info/METADATA
odoo_addon_contract_payment_mode-18.0.1.0.0.5.dist-info/WHEEL
odoo_addon_contract_payment_mode-18.0.1.0.0.5.dist-info/top_level.txt
odoo_addon_contract_payment_mode-18.0.1.0.0.5.dist-info/RECORD
