Metadata-Version: 2.1
Name: odoo-addon-contract_payment_mode
Version: 18.0.1.0.0.5
Requires-Python: >=3.10
Requires-Dist: odoo-addon-account_payment_partner==18.0.*
Requires-Dist: odoo-addon-contract==18.0.*
Requires-Dist: odoo==18.0.*
Summary: Payment mode in contracts and their invoices
Home-page: https://github.com/OCA/contract
License: AGPL-3
Author: Domatix, Tecnativa, Odoo Community Association (OCA)
Author-email: support@odoo-community.org
Classifier: Programming Language :: Python
Classifier: Framework :: Odoo
Classifier: Framework :: Odoo :: 18.0
Classifier: License :: OSI Approved :: GNU Affero General Public License v3
